pyspark_util/__init__.py
pyspark_util/dataframe.py
pyspark_util/version.py
pyspark_util-0.1.2.dist-info/METADATA
pyspark_util-0.1.2.dist-info/WHEEL
pyspark_util-0.1.2.dist-info/top_level.txt
pyspark_util-0.1.2.dist-info/RECORD
