Metadata-Version: 2.1
Name: pyspark-util
Version: 0.1.2
Summary: PySpark utility functions
Home-page: https://github.com/harupy/pyspark-util
Maintainer: harupy
Maintainer-email: hkawamura0130@gmail.com
License: UNKNOWN
Project-URL: Bug Tracker, https://github.com/harupy/pyspark-util/issues
Project-URL: Source Code, https://github.com/harupy/pyspark-util
Platform: UNKNOWN
Requires-Python: >=3.5
Requires-Dist: pyspark (>=2.4.4)
